{
	"one":[
		{
			"txt":"网络覆盖广",
			"num":"31",
			"tit":"个省份",
			"info":"在上海、北京、广州、苏州、武汉、成都、西安、沈阳等物流枢纽建有先进的仓储设施，在全国拥有总计100万余平方米普、冷、化仓储资源"
		},
		{
			"txt":"运输资源多",
			"num":"6",
			"tit":"万余台",
			"info":"自有运输车辆1500余台，通过自有运力平台可调动社会车辆资源60000余台 "
		},
		{
			"txt":"运输状态实时监控",
			"num":"",
			"tit":"监控中心",
			"info":"依靠自主研发系统，运用GPS实时监控货物在运输轨迹、车辆所在位置及车辆行驶里程等"
		}
	],
	"two":[
		{
			"src":"img/trunk-img-02.jpg",
			"tit":"甩挂运输",
			"txt":"通过高运输效率、高周转效率满足客户更高的时效要求，通过此运输模式对建设资源节约型、环境友好型社会也有重大的意义。"
		},
		{
			"src":"img/trunk-img-06.jpg",
			"tit":"冷链运输",
			"txt":"提供-30℃至25℃之间各类货物运输，精确的温控技术更能确保生物制品、药品的活性与安全。"
		},
		{
			"src":"img/trunk-img-05.jpg",
			"tit":"危险品运输",
			"txt":"经过国家相关职能部门严格审核，拥有能保证安全运输危险货物的相应设施设备、专业操作团队等，将货物安全、准时、准确的送达客户手中。"
		},
		{
			"src":"img/trunk-img-03.jpg",
			"tit":"班车运输",
			"txt":"开车定点班车专线，整合区域内货量集中发货，由各区域分公司进行统一协调配送，实现高时效、高服务质量的运输服务。"
		},
		{
			"src":"img/trunk-img.jpg",
			"tit":"铁路运输",
			"txt":"拥有丰富的可调动铁路运输资源，满足不同重量/体积货物类型的运输，满足客户大批量运输需求。"
		},
		{
			"src":"img/trunk-img-04.jpg",
			"tit":"航空运输",
			"txt":"拥有充足的航空运输资源，满足客户高时效要求。"
		}
	],
	"three":[
		{
			"tit":"定制化配送服务",
			"info":"根据不同的运输形式，模拟实验，分析物流费，配送Lead Time（交货期），装卸运营方式等，选择最佳的运输形式与线路设计"
		},
		{
			"tit":"智能城配系统",
			"info":"全国拥有120余家分支机构，运输配送网络覆盖全国，为客户提供最后一公里配送服务"
		},
		{
			"tit":"覆盖全国的<br/>配送分公司与网点",
			"info":"通过TMS等智能化调度系统，保障配送服务的准确与高效"
		}
	],
	"four":[
		{
			"img1":"img/delivery-img-04.jpg",
			"img2":"img/delivery-img-04@2x.jpg",
			"tit":"食品冷链配送",
			"txt":"实现同类产品优先配载、优先派送，拥有专业的配送设备设施及操作团队，保障生鲜食品的商品品质及配送时效。"
		},
		{
			"img1":"img/delivery-img-03.jpg",
			"img2":"img/delivery-img-03@2x.jpg",
			"tit":"医药冷链配送",
			"txt":"通过方舱、冷藏车等专业冷藏设备/车辆进行配送，对在途配送车辆进行全方位GPS监控，充分保证药品温度，确保生物制品、药品的活性与安全；"
		},
		{
			"img1":"img/delivery-img-05.jpg",
			"img2":"img/delivery-img-05@2x.jpg",
			"tit":"电子设备配送",
			"txt":"提供专业的运输防护，支持大型电子设备的卸货就位、上楼送货等；"
		},
		{
			"img1":"img/delivery-img-06.jpg",
			"img2":"img/delivery-img-06@2x.jpg",
			"tit":"化妆品配送",
			"txt":"提供多品类化妆品运输、分拣、二次包装、定时配送、送货上门/柜台等服务；"
		},
		{
			"img1":"img/delivery-img-07.jpg",
			"img2":"img/delivery-img-07@2x.jpg",
			"tit":"服装类配送",
			"txt":"提供鞋服运输、分拣、定时配送、送货上门的服务，能够满足客户多样化的需求；"
		},
		{
			"img1":"img/delivery-img-08.jpg",
			"img2":"img/delivery-img-08@2x.jpg",
			"tit":"汽车配件配送",
			"txt":"支持多品类配件、及适应品类的多种方式配送，满足客户多样化需求，另设置有丰富的配送网点，保证货物准时送达；"
		},
		{
			"img1":"img/delivery-img.jpg",
			"img2":"img/delivery-img@2x.jpg",
			"tit":"化工品配送",
			"txt":"拥有专业操作团队，提供不同于普通货物的操作与配送服务，既能保障操作效率与配送时效，又能保障货物安全；"
		},
		{
			"img1":"img/delivery-img-02.jpg",
			"img2":"img/delivery-img-02@2x.jpg",
			"tit":"危险品配送",
			"txt":"拥有专业操作团队和符合要求的专用车辆，针对货物品类制定有专门的应急预案，充分保障货物安全；"
		}
	]
}